md_summarizer/__init__.py
md_summarizer/agent/__init__.py
md_summarizer/agent/prompts.py
md_summarizer/agent/summarizer_agent.py
md_summarizer/common/__init__.py
md_summarizer/common/signals.py
md_summarizer/config/__init__.py
md_summarizer/config/settings.py
md_summarizer/core/summarizer.py
md_summarizer/models/__init__.py
md_summarizer/models/section.py
md_summarizer/parser/__init__.py
md_summarizer/parser/parser.py
md_summarizer/progress/__init__.py
md_summarizer/progress/models.py
md_summarizer-0.1.66.dist-info/METADATA
md_summarizer-0.1.66.dist-info/WHEEL
md_summarizer-0.1.66.dist-info/licenses/LICENSE
md_summarizer-0.1.66.dist-info/RECORD
