Metadata-Version: 2.4
Name: md_summarizer
Version: 0.1.66
Summary: AI-powered Markdown summarizer that preserves structure and code blocks
Project-URL: Homepage, https://github.com/celtiberi/md-summarizer
Project-URL: Bug Tracker, https://github.com/celtiberi/md-summarizer/issues
Project-URL: Source, https://github.com/celtiberi/md-summarizer
Author: Celtiberi
License-Expression: MIT
License-File: LICENSE
Keywords: ai,markdown,nlp,summarizer
Classifier: Development Status :: 4 - Beta
Classifier: Intended Audience :: Developers
Classifier: License :: OSI Approved :: MIT License
Classifier: Programming Language :: Python :: 3
Classifier: Programming Language :: Python :: 3.9
Classifier: Programming Language :: Python :: 3.10
Classifier: Programming Language :: Python :: 3.11
Requires-Python: >=3.11
Requires-Dist: blinker>=1.7.0
Requires-Dist: pydantic-ai>=0.0.18
Requires-Dist: pydantic-settings>=2.0.0
Requires-Dist: python-dotenv>=1.0.0
Requires-Dist: tiktoken>=0.5.0
Provides-Extra: test
Requires-Dist: pytest-asyncio>=0.21.0; extra == 'test'
Requires-Dist: pytest-watch>=4.2.0; extra == 'test'
Requires-Dist: pytest>=7.4.0; extra == 'test'
